{
    "results": [
        {
            "name": "Romania",
            "official_name": "Romania",
            "language": ["Romanian"],
            "demonym": "Romanian",
            "flag_picture": "N/A",
            "foundation": "January 24th, 1859",
            "continent": ["Europe"],
            "government_type": "Semi-presidential Representative Republic",
            "population": 19000000,
            "area_km_square": 238397,
            "fun_fact": "",
            "pictures": ["https://ichef.bbci.co.uk/ace/standard/976/cpsprodpb/D51D/production/_133675545_bbcm_country_profile_romania_kosovo_171224.jpg"]
        }
    ]
}